{
  "hash": "7ac8fb1c",
  "configHash": "497a9b7d",
  "lockfileHash": "ca29d3ba",
  "browserHash": "2fe2a7a6",
  "optimized": {
    "react": {
      "src": "../../node_modules/react/index.js",
      "file": "react.js",
      "fileHash": "d4fb306d",
      "needsInterop": true
    },
    "react-dom/client": {
      "src": "../../node_modules/react-dom/client.js",
      "file": "react-dom_client.js",
      "fileHash": "0782ba8d",
      "needsInterop": true
    },
    "react-router-dom": {
      "src": "../../node_modules/react-router-dom/dist/index.js",
      "file": "react-router-dom.js",
      "fileHash": "e8b88257",
      "needsInterop": false
    },
    "@mui/material/styles": {
      "src": "../../node_modules/@mui/material/styles/index.js",
      "file": "@mui_material_styles.js",
      "fileHash": "08d97438",
      "needsInterop": false
    },
    "@vercel/speed-insights/react": {
      "src": "../../node_modules/@vercel/speed-insights/dist/react/index.mjs",
      "file": "@vercel_speed-insights_react.js",
      "fileHash": "25f6e3c8",
      "needsInterop": false
    },
    "@vercel/analytics/react": {
      "src": "../../node_modules/@vercel/analytics/dist/react/index.js",
      "file": "@vercel_analytics_react.js",
      "fileHash": "d5ebf6b6",
      "needsInterop": false
    }
  },
  "chunks": {
    "chunk-UWZXFKA6": {
      "file": "chunk-UWZXFKA6.js"
    },
    "chunk-UPDK7Z2H": {
      "file": "chunk-UPDK7Z2H.js"
    }
  }
}